{
  "episodes": {
    "production": {},
    "test": {
      "validation_episodes_2_3": {
        "status": "completed",
        "description": "Episodes 2&3 validation testing",
        "quality_scores": {
          "ep2": 90.8,
          "ep3": 94.2
        }
      },
      "quantum_computing": {
        "status": "completed",
        "description": "Original quantum computing test episode",
        "cost": 5.51,
        "quality": 92.3
      }
    }
  },
  "totals": {
    "production": {
      "researched": 0,
      "produced": 0,
      "completed": 0,
      "total_cost": 0,
      "avg_cost": 0,
      "avg_quality": 0
    },
    "test": {
      "episodes_completed": 2,
      "total_cost": 25.01,
      "avg_quality": 92.4
    }
  },
  "batch": {
    "type": "research",
    "start": 1,
    "end": 3,
    "current": 3,
    "status": "completed",
    "last_updated": "2025-08-23T13:10:44Z"
  },
  "last_updated": "2025-08-23T08:55:00Z",
  "structure_version": "2.0.0"
}
